Workbook

Sheet Lisez-moi
A1: Catalogue de détection générique – SIEM / XDR
A2: v1.0 – 19/10/2026 – Référentiel indépendant du client et des technologies : les attaques les plus probables, les logs à collecter et la logique de règle à mettre en place.
A4: Principe
A5: Pour chaque attaque probable, le fichier donne : quoi détecter et dans quel domaine (feuille Detections), quels logs collecter et d'où (colonnes « Logs » et « Source », détaillées dans la feuille Sources_logs), et quelle logique de règle écrire. La logique est rédigée en langage courant : elle se traduit dans n'importe quel SIEM ou XDR (table plus bas).
A7: Utilisation en 5 étapes
A8: 1. Filtrer | B8: Filtrer la colonne Domaine selon les technologies du client (Windows, Linux, web, cloud…). Écarter les lignes sans objet.
A9: 2. Vérifier les logs | B9: Pour chaque ligne retenue, vérifier dans Sources_logs que la source est activée et collectée. Sinon le cas d'usage n'est pas détectable : le noter.
A10: 3. Écrire la règle | B10: Traduire la logique dans l'outil du client (table plus bas). Commencer par les lignes Critique et Haute de type Simple, puis les Corrélations.
A11: 4. Ajuster | B11: Les seuils, fenêtres et exclusions sont des points de départ : les ajuster après deux semaines d'observation.
A12: 5. Tester sans risque | B12: Rejouer un événement simulé ou une ligne de log, jamais l'attaque réelle (ni force brute, ni effacement de journaux, ni suppression de sauvegardes).
A14: Lire la feuille Detections
A15: Type | B15: Simple : un événement suffit. Seuil : N événements (ou N valeurs distinctes) dans une fenêtre de temps. Corrélation : une séquence A puis B, ou le croisement de deux sources, pour le même compte, hôte ou IP.
A16: Gravité | B16: Critique : compromission probable, réponse immédiate. Haute : activité malveillante probable, traitement rapide. Moyenne : à investiguer. Basse : reconnaissance ou contexte, utile pour enrichir.
A17: Logique de la règle | B17: SI … PUIS … → alerte. « PUIS » impose l'ordre des événements ; « ≥ N » signifie au moins N. Les exclusions à prévoir (comptes de service, scanners, outils de déploiement) sont citées dans le texte.
A18: MITRE ATT&CK | B18: Techniques de la version 19.2 de MITRE ATT&CK, avec leur intitulé officiel.
A20: Traduire la logique dans votre SIEM / XDR
A21: Notion | B21: Wazuh | C21: Splunk | D21: Microsoft Sentinel / Defender XDR (KQL) | E21: Elastic Security
A22: Seuil : N événements en T | B22: Règle avec frequency et timeframe (same_source_ip, same_user) | C22: Recherche planifiée : stats count by … | where count > N | D22: summarize count() by …, bin(TimeGenerated, T) | where count_ > N | E22: Règle de type Threshold
A23: Corrélation : A puis B | B23: Règle fille avec if_matched_sid ou if_matched_group et timeframe | C23: transaction, ou stats sur la clé commune (compte, IP, hôte) dans la fenêtre | D23: join de deux requêtes dans une fenêtre de temps | E23: EQL : sequence by <clé> with maxspan=T [A] [B]
A24: Valeurs distinctes : ≥ N comptes, ports, hôtes | B24: different_field avec frequency | C24: stats dc(champ) by … | D24: summarize dcount(champ) by … | E24: Threshold avec condition de cardinalité
A25: Liste de référence : comptes admin, IOC, serveurs | B25: Liste CDB (<list>) | C25: Lookup | D25: Watchlist | E25: Value list, ou règle Indicator Match
A26: Pour un autre XDR, reprendre la même logique dans le langage de règles personnalisées de l'outil. Les listes de référence (comptes d'administration habilités, serveurs, adresses malveillantes) évitent d'écrire des valeurs en dur dans les règles.
A28: Domaines couverts
A29: Domaine | B29: Cas d'usage | C29: dont Simple | D29: dont Seuil | E29: dont Corrélation
A30: Identité & AD | B30: =COUNTIF(Detections!$B$2:$B$83,$A30) -> 10 | C30: =COUNTIFS(Detections!$B$2:$B$83,$A30,Detections!$D$2:$D$83,"Simple") -> 3 | D30: =COUNTIFS(Detections!$B$2:$B$83,$A30,Detections!$D$2:$D$83,"Seuil") -> 3 | E30: =COUNTIFS(Detections!$B$2:$B$83,$A30,Detections!$D$2:$D$83,"Corrélation") -> 4
A31: Poste & serveur Windows | B31: =COUNTIF(Detections!$B$2:$B$83,$A31) -> 11 | C31: =COUNTIFS(Detections!$B$2:$B$83,$A31,Detections!$D$2:$D$83,"Simple") -> 8 | D31: =COUNTIFS(Detections!$B$2:$B$83,$A31,Detections!$D$2:$D$83,"Seuil") -> 1 | E31: =COUNTIFS(Detections!$B$2:$B$83,$A31,Detections!$D$2:$D$83,"Corrélation") -> 2
A32: Linux / Unix | B32: =COUNTIF(Detections!$B$2:$B$83,$A32) -> 7 | C32: =COUNTIFS(Detections!$B$2:$B$83,$A32,Detections!$D$2:$D$83,"Simple") -> 5 | D32: =COUNTIFS(Detections!$B$2:$B$83,$A32,Detections!$D$2:$D$83,"Seuil") -> 0 | E32: =COUNTIFS(Detections!$B$2:$B$83,$A32,Detections!$D$2:$D$83,"Corrélation") -> 2
A33: Web & applications | B33: =COUNTIF(Detections!$B$2:$B$83,$A33) -> 8 | C33: =COUNTIFS(Detections!$B$2:$B$83,$A33,Detections!$D$2:$D$83,"Simple") -> 3 | D33: =COUNTIFS(Detections!$B$2:$B$83,$A33,Detections!$D$2:$D$83,"Seuil") -> 2 | E33: =COUNTIFS(Detections!$B$2:$B$83,$A33,Detections!$D$2:$D$83,"Corrélation") -> 3
A34: Réseau & périmètre | B34: =COUNTIF(Detections!$B$2:$B$83,$A34) -> 10 | C34: =COUNTIFS(Detections!$B$2:$B$83,$A34,Detections!$D$2:$D$83,"Simple") -> 3 | D34: =COUNTIFS(Detections!$B$2:$B$83,$A34,Detections!$D$2:$D$83,"Seuil") -> 4 | E34: =COUNTIFS(Detections!$B$2:$B$83,$A34,Detections!$D$2:$D$83,"Corrélation") -> 3
A35: Messagerie & SaaS | B35: =COUNTIF(Detections!$B$2:$B$83,$A35) -> 8 | C35: =COUNTIFS(Detections!$B$2:$B$83,$A35,Detections!$D$2:$D$83,"Simple") -> 4 | D35: =COUNTIFS(Detections!$B$2:$B$83,$A35,Detections!$D$2:$D$83,"Seuil") -> 0 | E35: =COUNTIFS(Detections!$B$2:$B$83,$A35,Detections!$D$2:$D$83,"Corrélation") -> 4
A36: Cloud | B36: =COUNTIF(Detections!$B$2:$B$83,$A36) -> 7 | C36: =COUNTIFS(Detections!$B$2:$B$83,$A36,Detections!$D$2:$D$83,"Simple") -> 4 | D36: =COUNTIFS(Detections!$B$2:$B$83,$A36,Detections!$D$2:$D$83,"Seuil") -> 2 | E36: =COUNTIFS(Detections!$B$2:$B$83,$A36,Detections!$D$2:$D$83,"Corrélation") -> 1
A37: Bases de données & données | B37: =COUNTIF(Detections!$B$2:$B$83,$A37) -> 7 | C37: =COUNTIFS(Detections!$B$2:$B$83,$A37,Detections!$D$2:$D$83,"Simple") -> 2 | D37: =COUNTIFS(Detections!$B$2:$B$83,$A37,Detections!$D$2:$D$83,"Seuil") -> 3 | E37: =COUNTIFS(Detections!$B$2:$B$83,$A37,Detections!$D$2:$D$83,"Corrélation") -> 2
A38: Conteneurs & virtualisation | B38: =COUNTIF(Detections!$B$2:$B$83,$A38) -> 4 | C38: =COUNTIFS(Detections!$B$2:$B$83,$A38,Detections!$D$2:$D$83,"Simple") -> 3 | D38: =COUNTIFS(Detections!$B$2:$B$83,$A38,Detections!$D$2:$D$83,"Seuil") -> 0 | E38: =COUNTIFS(Detections!$B$2:$B$83,$A38,Detections!$D$2:$D$83,"Corrélation") -> 1
A39: Ransomware & malware | B39: =COUNTIF(Detections!$B$2:$B$83,$A39) -> 6 | C39: =COUNTIFS(Detections!$B$2:$B$83,$A39,Detections!$D$2:$D$83,"Simple") -> 2 | D39: =COUNTIFS(Detections!$B$2:$B$83,$A39,Detections!$D$2:$D$83,"Seuil") -> 1 | E39: =COUNTIFS(Detections!$B$2:$B$83,$A39,Detections!$D$2:$D$83,"Corrélation") -> 3
A40: Santé du SOC | B40: =COUNTIF(Detections!$B$2:$B$83,$A40) -> 4 | C40: =COUNTIFS(Detections!$B$2:$B$83,$A40,Detections!$D$2:$D$83,"Simple") -> 2 | D40: =COUNTIFS(Detections!$B$2:$B$83,$A40,Detections!$D$2:$D$83,"Seuil") -> 2 | E40: =COUNTIFS(Detections!$B$2:$B$83,$A40,Detections!$D$2:$D$83,"Corrélation") -> 0
A41: Total | B41: =SUM(B30:B40) -> 82 | C41: =SUM(C30:C40) -> 39 | D41: =SUM(D30:D40) -> 18 | E41: =SUM(E30:E40) -> 25

Sheet Detections
A1: ID | B1: Domaine | C1: Cas d'usage (attaque détectée) | D1: Type | E1: Logs à collecter | F1: Source des logs | G1: Logique de la règle | H1: Gravité | I1: MITRE ATT&CK
A2: DET-001 | B2: Identité & AD | C2: Force brute suivie d'une connexion réussie | D2: Corrélation | E2: Échecs et succès d'authentification : Windows 4625 / 4624 (+ 4771, 4776), SSH et sudo, SSO / IdP (résultat, compte, IP source), VPN. | F2: AD – contrôleurs de domaine SSO / fournisseur d'identité Linux – auth, syslog, auditd VPN / accès distant | G2: SI ≥ 8 échecs d'authentification sur un même compte, ou depuis une même IP source, en 10 min, PUIS 1 succès de ce compte depuis cette IP dans les 30 min → alerte. Exclure les comptes de service connus et les scanners de vulnérabilités autorisés. | H2: Haute | I2: T1110.001 Password Guessing T1078 Valid Accounts
A3: DET-002 | B3: Identité & AD | C3: Password spraying (un mot de passe sur de nombreux comptes) | D3: Corrélation | E3: Échecs d'authentification avec compte et IP source : Windows 4625 / 4771 / 4776, SSO / IdP, connexions Entra ID ou Google Workspace. | F3: AD – contrôleurs de domaine SSO / fournisseur d'identité Messagerie / SaaS (M365, Google) | G3: SI une même IP source échoue sur ≥ 10 comptes distincts en 15 min (peu d'essais par compte) → alerte ; SI l'un de ces comptes réussit PUIS, depuis cette IP ou une IP du même réseau, dans les 60 min → critique. | H3: Haute | I3: T1110.003 Password Spraying T1078 Valid Accounts
A4: DET-003 | B4: Identité & AD | C4: Verrouillages de comptes en masse | D4: Seuil | E4: Windows 4740 (compte verrouillé), événements de verrouillage du SSO / LDAP, avec le nom de la machine ou l'IP à l'origine. | F4: AD – contrôleurs de domaine SSO / fournisseur d'identité | G4: SI ≥ 5 comptes distincts sont verrouillés en 10 min → alerte (spraying ou déni de service sur les comptes). Rapprocher de l'IP source des échecs 4625 / 4771. | H4: Moyenne | I4: T1110 Brute Force
A5: DET-004 | B5: Identité & AD | C5: Connexion impossible ou provenance inhabituelle | D5: Corrélation | E5: Connexions réussies avec IP source et géolocalisation : VPN, SSO, connexions M365 / Entra ID ou Google Workspace, webmail. | F5: VPN / accès distant SSO / fournisseur d'identité Messagerie / SaaS (M365, Google) | G5: SI une connexion réussie d'un compte est suivie PUIS, en ≤ 12 h, d'une connexion réussie du même compte depuis un autre pays impliquant une vitesse de déplacement > 900 km/h (distance divisée par le temps écoulé), OU si la connexion vient d'un pays jamais vu pour ce compte en 30 jours → alerte. Exclure les IP des VPN et proxys d'entreprise. | H5: Moyenne | I5: T1078 Valid Accounts
A6: DET-005 | B6: Identité & AD | C6: Création d'un compte puis ajout à un groupe privilégié | D6: Corrélation | E6: Création : Windows 4720, Linux « new user » (useradd), cloud CreateUser. Ajout au groupe : Windows 4728 / 4732 / 4756, usermod -aG sudo, AttachUserPolicy. | F6: AD – contrôleurs de domaine Windows – journal Security Linux – auth, syslog, auditd Cloud – audit des API | G6: SI création d'un compte PUIS ajout de ce même compte à un groupe privilégié (Domain Admins, Enterprise Admins, Administrateurs locaux, sudo / wheel, rôle d'administration cloud) en ≤ 60 min, par le même acteur → critique. | H6: Critique | I6: T1136 Create Account T1098 Account Manipulation
A7: DET-006 | B7: Identité & AD | C7: Ajout d'un membre à un groupe privilégié hors processus | D7: Simple | E7: Windows 4728 / 4732 / 4756 (ajout), 4729 / 4733 (retrait) sur les groupes Domain Admins, Enterprise Admins, Schema Admins, Administrators, Account Operators, Backup Operators. | F7: AD – contrôleurs de domaine | G7: SI un membre est ajouté à un groupe de la liste privilégiée par un acteur absent de la liste des administrateurs habilités, ou en dehors d'une fenêtre de changement → alerte haute. | H7: Haute | I7: T1098 Account Manipulation
A8: DET-007 | B8: Identité & AD | C8: Kerberoasting et AS-REP roasting | D8: Seuil | E8: Windows 4769 (ticket de service : type de chiffrement, nom du service) et 4768 (ticket initial : type de pré-authentification). | F8: AD – contrôleurs de domaine | G8: Kerberoasting : SI un même compte demande ≥ 5 tickets de service distincts en chiffrement RC4 (0x17), hors comptes machine ($) et krbtgt, en 5 min → alerte. AS-REP roasting : SI 4768 avec type de pré-authentification 0 (pré-authentification désactivée sur le compte) → alerte. | H8: Haute | I8: T1558.003 Kerberoasting T1558.004 AS-REP Roasting
A9: DET-008 | B9: Identité & AD | C9: DCSync (réplication d'annuaire par un compte non contrôleur) | D9: Simple | E9: Windows 4662 avec le droit de réplication DS-Replication-Get-Changes-All (GUID 1131f6ad-9c07-11d1-f79f-00c04fc2dcd2). | F9: AD – contrôleurs de domaine | G9: SI un 4662 portant ce droit est déclenché par un compte qui n'est ni un contrôleur de domaine ni un compte de synchronisation d'annuaire connu → critique. L'audit « Directory Service Access » et un audit (SACL) sur l'objet domaine sont nécessaires. | H9: Critique | I9: T1003.006 DCSync
A10: DET-009 | B10: Identité & AD | C10: Mouvement latéral par compte administrateur (Pass-the-Hash) | D10: Seuil | E10: Windows 4624 type 3 (réseau) avec authentification NTLM, 4672 (privilèges spéciaux), 4776. | F10: Windows – journal Security AD – contrôleurs de domaine | G10: SI un même compte ouvre des sessions réseau NTLM sur ≥ 5 machines distinctes en 10 min → alerte haute. Exclure les comptes de supervision, d'inventaire et de déploiement. | H10: Haute | I10: T1550.002 Pass the Hash T1021.002 SMB/Windows Admin Shares
A11: DET-010 | B11: Identité & AD | C11: Modification d'objets sensibles de l'annuaire (GPO, AdminSDHolder, approbations) | D11: Simple | E11: Windows 5136 (objet modifié), 5137 (créé), 5141 (supprimé) sur groupPolicyContainer, AdminSDHolder et objets d'approbation ; 4739 (stratégie de domaine modifiée). | F11: AD – contrôleurs de domaine | G11: SI une GPO liée à la racine du domaine ou aux contrôleurs, l'objet AdminSDHolder ou une relation d'approbation est modifié par un compte hors équipe annuaire → alerte haute. | H11: Haute | I11: T1484.001 Group Policy Modification T1484.002 Trust Modification
A12: DET-011 | B12: Poste & serveur Windows | C12: Journal d'événements effacé | D12: Simple | E12: Windows 1102 (journal Security effacé), 104 (journal System ou applicatif effacé). | F12: Windows – journal Security Windows – System et Defender | G12: SI événement 1102 ou 104 → alerte critique, sauf maintenance planifiée documentée. Relever le compte qui a lancé l'effacement. | H12: Critique | I12: T1685.005 Clear Windows Event Logs
... A83: DET-082 | B83: Santé du SOC | C83: Modification de la configuration du SIEM ou du XDR | D83: Simple | E83: Journal d'audit du SIEM / XDR : règle désactivée ou modifiée, exclusion ajoutée, rétention changée, compte administrateur créé. | F83: SIEM / XDR (santé) | G83: SI une règle est désactivée ou modifiée, une exclusion ajoutée, la rétention réduite ou un compte administrateur créé hors changement approuvé → alerte haute. | H83: Haute | I83: T1685 Disable or Modify Tools

Sheet Sources_logs
A1: Source des logs | B1: À activer / à collecter | C1: Événements ou champs clés | D1: Piège fréquent | E1: Cas d'usage servis
A2: AD – contrôleurs de domaine | B2: Audit avancé sur les contrôleurs : Account Logon (Kerberos, NTLM), Account Management, DS Access (accès et modifications de l'annuaire), Policy Change. Collecter TOUS les contrôleurs de domaine. | C2: 4624, 4625, 4662, 4720, 4728, 4729, 4732, 4733, 4739, 4740, 4756, 4768, 4769, 4771, 4776, 5136, 5137, 5141 | D2: Chaque événement n'existe que sur le contrôleur qui traite la requête : en oublier un crée un angle mort. Le 4662 n'apparaît que si un audit (SACL) est posé sur l'objet domaine. | E2: =COUNTIF(Detections!$F$2:$F$83,"*"&A2&"*") -> 9
A3: Windows – journal Security | B3: Sur les serveurs et les postes, audit avancé : Logon / Logoff, Account Management, Process Creation avec ligne de commande (GPO « Inclure la ligne de commande dans les événements de création de processus »), Detailed File Share, Other Object Access (tâches planifiées), Security System Extension (services). | C3: 1102, 4624, 4625, 4672, 4688, 4697, 4698, 4720, 4728, 4732, 4756, 4778, 4779, 5145 | D3: La ligne de commande du 4688 est absente sans la GPO dédiée. Le 5145 est très volumineux et certains agents le filtrent par défaut : vérifier la liste d'exclusion. | E3: =COUNTIF(Detections!$F$2:$F$83,"*"&A3&"*") -> 12
A4: Windows – Sysmon | B4: Installer Sysmon avec une configuration éprouvée (configuration communautaire à adapter), puis collecter le canal Microsoft-Windows-Sysmon/Operational. | C4: 1 (processus), 10 (accès à un processus), 11 (création de fichier), 13 (valeur de registre), 23 (suppression de fichier) | D4: Absent par défaut ; sans configuration le volume explose. Filtrer l'événement 10 sur la cible lsass.exe. | E4: =COUNTIF(Detections!$F$2:$F$83,"*"&A4&"*") -> 13
A5: Windows – PowerShell | B5: Activer la journalisation des blocs de script (GPO « Turn on PowerShell Script Block Logging ») et collecter le canal Microsoft-Windows-PowerShell/Operational. | C5: 4104 (bloc de script), 4103 (module) | D5: Désactivée par défaut. Le journal peut contenir des secrets en clair : en restreindre l'accès. PowerShell 2.0 n'est pas journalisé : le retirer des postes. | E5: =COUNTIF(Detections!$F$2:$F$83,"*"&A5&"*") -> 2
A6: Windows – System et Defender | B6: Collecter les canaux System et Microsoft-Windows-Windows Defender/Operational. | C6: System : 104, 7036, 7045 ; Defender : 1116, 1117, 5001, 5007 | D6: Les événements Defender n'existent que si Defender est l'antivirus actif ; sinon utiliser les alertes de l'EDR ou de l'antivirus en place. | E6: =COUNTIF(Detections!$F$2:$F$83,"*"&A6&"*") -> 7
A7: SSO / fournisseur d'identité | B7: Journaliser chaque authentification du SSO, du LDAP ou de l'IAM (résultat, compte, IP source, application, facteur MFA) et les actions d'administration ; export syslog ou API vers le SIEM. | C7: Succès, échec, verrouillage, MFA demandé ou refusé, changement de mot de passe, ajout à un groupe | D7: Vérifier le fuseau horaire et que l'IP source est bien celle du client (et non celle d'un proxy ou de l'IdP). | E7: =COUNTIF(Detections!$F$2:$F$83,"*"&A7&"*") -> 6
A8: Linux – auth, syslog, auditd | B8: Collecter /var/log/auth.log (Debian, Ubuntu) ou /var/log/secure (RHEL et dérivés) ; activer auditd avec des règles sur execve, les fichiers d'authentification et les changements de comptes. | C8: sshd (Failed, Accepted), sudo (COMMAND=, authentication failure), su, useradd, usermod, auditd EXECVE et SYSCALL | D8: auditd n'a pas de règles utiles par défaut. Sans l'audit de execve, la ligne de commande des processus n'est pas disponible. | E8: =COUNTIF(Detections!$F$2:$F$83,"*"&A8&"*") -> 9
A9: Intégrité des fichiers (FIM) | B9: Surveiller en temps réel les répertoires sensibles : racine web, /etc, ~/.ssh, cron et systemd (Linux), dossiers de démarrage et partages (Windows). | C9: Création, modification, suppression ; hash avant et après ; utilisateur et processus si disponibles | D9: Beaucoup d'agents n'analysent qu'à intervalle fixe (souvent plusieurs heures) : passer en temps réel pour détecter webshells et chiffrement. | E9: =COUNTIF(Detections!$F$2:$F$83,"*"&A9&"*") -> 7
A10: Serveur web (IIS, Apache, Nginx) | B10: Collecter les journaux d'accès et d'erreur (IIS au format W3C, Apache, Nginx, Tomcat) avec IP source, méthode, URI et paramètres, code HTTP, taille, User-Agent, X-Forwarded-For. | C10: Code HTTP, URI, paramètres, User-Agent, taille de la réponse | D10: Derrière un reverse proxy ou un WAF, l'IP vue est celle du proxy : journaliser X-Forwarded-For. Le corps des requêtes POST n'est pas journalisé. | E10: =COUNTIF(Detections!$F$2:$F$83,"*"&A10&"*") -> 6
A11: WAF / reverse proxy | B11: Envoyer les journaux du WAF : décision (bloquer, autoriser), règle déclenchée, URI, IP source. | C11: Action, identifiant de règle, URI, IP source, pays | D11: En mode détection seule, aucune requête n'est bloquée : le journal indique l'intention, pas l'effet. Volume élevé en JSON. | E11: =COUNTIF(Detections!$F$2:$F$83,"*"&A11&"*") -> 7
A12: Application métier / API | B12: Journaliser authentifications, accès aux objets (identifiant, résultat) et actions sensibles dans un format structuré (JSON), avec compte, IP source et identifiant de session. | C12: Compte, action, objet, résultat, IP source | D12: Les formats libres imposent un travail de normalisation avant d'écrire la moindre règle. | E12: =COUNTIF(Detections!$F$2:$F$83,"*"&A12&"*") -> 2
A13: Pare-feu | B13: Journaliser tous les flux (autorisés et refusés), les événements IPS / UTM et le journal d'administration (connexions, changements de configuration) ; envoi syslog vers le collecteur. | C13: IP et port source et destination, action, règle, octets ; connexions d'administration ; modifications de configuration | D13: Beaucoup de pare-feu ne journalisent pas les flux autorisés par défaut. Vérifier le transport accepté par le SIEM (UDP, TCP, TLS). | E13: =COUNTIF(Detections!$F$2:$F$83,"*"&A13&"*") -> 12
... A29: SIEM / XDR (santé) | B29: Superviser le dernier événement reçu par source, l'état des agents, le volume (EPS) par source et les actions d'administration du SIEM / XDR. | C29: Dernier événement par source, agent déconnecté, volume par source, modification de règle | D29: Le SOC ne voit pas ce qu'il ne reçoit plus : sans ces règles, une source muette passe inaperçue. | E29: =COUNTIF(Detections!$F$2:$F$83,"*"&A29&"*") -> 4
